{
  "version": 1,
  "updated_at": "2026-05-03T00:09:36.023Z",
  "notifications": [
    {
      "key": "clawsweeper.repair_blocked:openclaw/openclaw:target-unknown:repair_contributor_branch:failed:2026-05-03T00:09:15.277Z",
      "idempotencyKey": "clawsweeper.repair_blocked:openclaw/openclaw:target-unknown:repair_contributor_branch:failed:2026-05-03T00:09:15.277Z",
      "type": "clawsweeper.repair_blocked",
      "severity": "error",
      "repo": "openclaw/openclaw",
      "target": null,
      "title": null,
      "url": null,
      "action": "repair_contributor_branch",
      "status": "failed",
      "reason": "Codex /review timed out after 150905ms",
      "runId": "25264642749",
      "runUrl": "https://github.com/openclaw/clawsweeper/actions/runs/25264642749",
      "clusterId": "automerge-openclaw-openclaw-75135",
      "publishedAt": "2026-05-03T00:09:15.277Z",
      "details": {
        "action": "repair_contributor_branch",
        "status": "failed",
        "target": null,
        "pr": null,
        "branch": null,
        "source_action": null,
        "source_status": null,
        "repair_strategy": null,
        "reason": "Codex /review timed out after 150905ms",
        "title": null,
        "url": null
      },
      "notifiedAt": "2026-05-03T00:09:36.023Z",
      "hookRunId": "14c44217-96d1-458e-93b7-92e47a37c2b0",
      "discordTarget": "channel:1499243561407741994"
    }
  ]
}
