[
  {
    "number": 52365,
    "action": "review_comment_synced",
    "reason": "updated durable Codex review comment"
  },
  {
    "number": 58067,
    "action": "review_comment_synced",
    "reason": "updated durable Codex review comment"
  },
  {
    "number": 58161,
    "action": "review_comment_synced",
    "reason": "updated durable Codex review comment"
  },
  {
    "number": 58284,
    "action": "review_comment_synced",
    "reason": "updated durable Codex review comment"
  },
  {
    "number": 58893,
    "action": "review_comment_synced",
    "reason": "updated durable Codex review comment"
  },
  {
    "number": 58905,
    "action": "review_comment_synced",
    "reason": "updated durable Codex review comment"
  },
  {
    "number": 58908,
    "action": "review_comment_synced",
    "reason": "updated durable Codex review comment"
  },
  {
    "number": 58940,
    "action": "review_comment_synced",
    "reason": "updated durable Codex review comment"
  },
  {
    "number": 58944,
    "action": "review_comment_synced",
    "reason": "updated durable Codex review comment"
  },
  {
    "number": 58949,
    "action": "review_comment_synced",
    "reason": "updated durable Codex review comment"
  },
  {
    "number": 58957,
    "action": "review_comment_synced",
    "reason": "updated durable Codex review comment"
  },
  {
    "number": 58968,
    "action": "review_comment_synced",
    "reason": "updated durable Codex review comment"
  },
  {
    "number": 58971,
    "action": "review_comment_synced",
    "reason": "updated durable Codex review comment"
  },
  {
    "number": 58987,
    "action": "review_comment_synced",
    "reason": "updated durable Codex review comment"
  },
  {
    "number": 58993,
    "action": "review_comment_synced",
    "reason": "updated durable Codex review comment"
  },
  {
    "number": 59002,
    "action": "review_comment_synced",
    "reason": "updated durable Codex review comment"
  },
  {
    "number": 59013,
    "action": "review_comment_synced",
    "reason": "updated durable Codex review comment"
  },
  {
    "number": 59078,
    "action": "review_comment_synced",
    "reason": "updated durable Codex review comment"
  },
  {
    "number": 59083,
    "action": "review_comment_synced",
    "reason": "updated durable Codex review comment"
  },
  {
    "number": 59086,
    "action": "review_comment_synced",
    "reason": "updated durable Codex review comment"
  },
  {
    "number": 59109,
    "action": "review_comment_synced",
    "reason": "updated durable Codex review comment"
  },
  {
    "number": 59115,
    "action": "review_comment_synced",
    "reason": "updated durable Codex review comment"
  },
  {
    "number": 59130,
    "action": "review_comment_synced",
    "reason": "updated durable Codex review comment"
  },
  {
    "number": 59137,
    "action": "review_comment_synced",
    "reason": "updated durable Codex review comment"
  },
  {
    "number": 59141,
    "action": "review_comment_synced",
    "reason": "updated durable Codex review comment"
  },
  {
    "number": 59149,
    "action": "review_comment_synced",
    "reason": "updated durable Codex review comment"
  },
  {
    "number": 59164,
    "action": "review_comment_synced",
    "reason": "updated durable Codex review comment"
  },
  {
    "number": 59168,
    "action": "review_comment_synced",
    "reason": "updated durable Codex review comment"
  },
  {
    "number": 59170,
    "action": "review_comment_synced",
    "reason": "updated durable Codex review comment"
  },
  {
    "number": 59172,
    "action": "review_comment_synced",
    "reason": "updated durable Codex review comment"
  },
  {
    "number": 59177,
    "action": "review_comment_synced",
    "reason": "updated durable Codex review comment"
  },
  {
    "number": 59196,
    "action": "review_comment_synced",
    "reason": "updated durable Codex review comment; synced durable PR egg comment"
  },
  {
    "number": 59208,
    "action": "review_comment_synced",
    "reason": "updated durable Codex review comment"
  },
  {
    "number": 59214,
    "action": "review_comment_synced",
    "reason": "updated durable Codex review comment"
  },
  {
    "number": 59221,
    "action": "review_comment_synced",
    "reason": "updated durable Codex review comment"
  },
  {
    "number": 59225,
    "action": "review_comment_synced",
    "reason": "updated durable Codex review comment"
  },
  {
    "number": 59235,
    "action": "review_comment_synced",
    "reason": "updated durable Codex review comment"
  },
  {
    "number": 59245,
    "action": "review_comment_synced",
    "reason": "updated durable Codex review comment"
  },
  {
    "number": 59280,
    "action": "review_comment_synced",
    "reason": "updated durable Codex review comment"
  },
  {
    "number": 59281,
    "action": "review_comment_synced",
    "reason": "updated durable Codex review comment"
  },
  {
    "number": 59285,
    "action": "review_comment_synced",
    "reason": "updated durable Codex review comment"
  },
  {
    "number": 59298,
    "action": "review_comment_synced",
    "reason": "updated durable Codex review comment"
  },
  {
    "number": 59299,
    "action": "review_comment_synced",
    "reason": "updated durable Codex review comment"
  },
  {
    "number": 59330,
    "action": "review_comment_synced",
    "reason": "updated durable Codex review comment"
  },
  {
    "number": 59336,
    "action": "review_comment_synced",
    "reason": "updated durable Codex review comment"
  },
  {
    "number": 59339,
    "action": "review_comment_synced",
    "reason": "updated durable Codex review comment"
  },
  {
    "number": 59349,
    "action": "review_comment_synced",
    "reason": "updated durable Codex review comment"
  },
  {
    "number": 59360,
    "action": "review_comment_synced",
    "reason": "updated durable Codex review comment"
  },
  {
    "number": 59361,
    "action": "review_comment_synced",
    "reason": "updated durable Codex review comment"
  },
  {
    "number": 59365,
    "action": "review_comment_synced",
    "reason": "updated durable Codex review comment; synced durable PR egg comment"
  },
  {
    "number": 59366,
    "action": "review_comment_synced",
    "reason": "updated durable Codex review comment"
  },
  {
    "number": 59382,
    "action": "review_comment_synced",
    "reason": "updated durable Codex review comment"
  },
  {
    "number": 59389,
    "action": "review_comment_synced",
    "reason": "updated durable Codex review comment"
  },
  {
    "number": 59414,
    "action": "review_comment_synced",
    "reason": "updated durable Codex review comment"
  },
  {
    "number": 59416,
    "action": "review_comment_synced",
    "reason": "updated durable Codex review comment"
  },
  {
    "number": 59484,
    "action": "review_comment_synced",
    "reason": "updated durable Codex review comment"
  },
  {
    "number": 59490,
    "action": "review_comment_synced",
    "reason": "updated durable Codex review comment"
  },
  {
    "number": 59523,
    "action": "review_comment_synced",
    "reason": "updated durable Codex review comment"
  },
  {
    "number": 59526,
    "action": "review_comment_synced",
    "reason": "updated durable Codex review comment"
  },
  {
    "number": 59528,
    "action": "review_comment_synced",
    "reason": "updated durable Codex review comment"
  },
  {
    "number": 59532,
    "action": "review_comment_synced",
    "reason": "updated durable Codex review comment"
  },
  {
    "number": 59563,
    "action": "review_comment_synced",
    "reason": "updated durable Codex review comment"
  },
  {
    "number": 59572,
    "action": "review_comment_synced",
    "reason": "updated durable Codex review comment"
  },
  {
    "number": 59597,
    "action": "review_comment_synced",
    "reason": "updated durable Codex review comment"
  },
  {
    "number": 59662,
    "action": "review_comment_synced",
    "reason": "updated durable Codex review comment"
  },
  {
    "number": 59665,
    "action": "review_comment_synced",
    "reason": "updated durable Codex review comment"
  },
  {
    "number": 59692,
    "action": "review_comment_synced",
    "reason": "updated durable Codex review comment; synced durable PR egg comment"
  },
  {
    "number": 59694,
    "action": "review_comment_synced",
    "reason": "updated durable Codex review comment; synced durable PR egg comment"
  },
  {
    "number": 59695,
    "action": "review_comment_synced",
    "reason": "updated durable Codex review comment; synced durable PR egg comment"
  },
  {
    "number": 59697,
    "action": "review_comment_synced",
    "reason": "updated durable Codex review comment"
  },
  {
    "number": 59705,
    "action": "review_comment_synced",
    "reason": "updated durable Codex review comment; synced durable PR egg comment"
  },
  {
    "number": 59719,
    "action": "review_comment_synced",
    "reason": "updated durable Codex review comment"
  },
  {
    "number": 59727,
    "action": "review_comment_synced",
    "reason": "updated durable Codex review comment"
  },
  {
    "number": 59737,
    "action": "review_comment_synced",
    "reason": "updated durable Codex review comment"
  },
  {
    "number": 59740,
    "action": "review_comment_synced",
    "reason": "updated durable Codex review comment"
  },
  {
    "number": 59745,
    "action": "review_comment_synced",
    "reason": "updated durable Codex review comment"
  },
  {
    "number": 59746,
    "action": "review_comment_synced",
    "reason": "updated durable Codex review comment"
  },
  {
    "number": 59747,
    "action": "review_comment_synced",
    "reason": "updated durable Codex review comment"
  },
  {
    "number": 59752,
    "action": "skipped_same_author_pair",
    "reason": "open issue #59743 ([Bug]: shouldSuppressMessagingToolReplies drops legitimate final reply when message tool sent media-only to same channel) by the same author is paired with this PR"
  },
  {
    "number": 59771,
    "action": "review_comment_synced",
    "reason": "updated durable Codex review comment"
  },
  {
    "number": 59801,
    "action": "review_comment_synced",
    "reason": "updated durable Codex review comment"
  }
]