[
  {
    "number": 43938,
    "action": "review_comment_synced",
    "reason": "updated durable Codex review comment"
  },
  {
    "number": 43953,
    "action": "review_comment_synced",
    "reason": "updated durable Codex review comment"
  },
  {
    "number": 43984,
    "action": "review_comment_synced",
    "reason": "updated durable Codex review comment"
  },
  {
    "number": 44015,
    "action": "review_comment_synced",
    "reason": "updated durable Codex review comment"
  },
  {
    "number": 44049,
    "action": "review_comment_synced",
    "reason": "updated durable Codex review comment"
  },
  {
    "number": 44086,
    "action": "review_comment_synced",
    "reason": "updated durable Codex review comment"
  },
  {
    "number": 44167,
    "action": "review_comment_synced",
    "reason": "updated durable Codex review comment"
  },
  {
    "number": 44215,
    "action": "review_comment_synced",
    "reason": "updated durable Codex review comment"
  },
  {
    "number": 44228,
    "action": "review_comment_synced",
    "reason": "updated durable Codex review comment"
  },
  {
    "number": 44316,
    "action": "review_comment_synced",
    "reason": "updated durable Codex review comment"
  },
  {
    "number": 44379,
    "action": "review_comment_synced",
    "reason": "updated durable Codex review comment"
  },
  {
    "number": 44460,
    "action": "review_comment_synced",
    "reason": "updated durable Codex review comment"
  },
  {
    "number": 44475,
    "action": "review_comment_synced",
    "reason": "updated durable Codex review comment"
  },
  {
    "number": 44510,
    "action": "review_comment_synced",
    "reason": "updated durable Codex review comment"
  },
  {
    "number": 44523,
    "action": "review_comment_synced",
    "reason": "updated durable Codex review comment"
  },
  {
    "number": 44534,
    "action": "review_comment_synced",
    "reason": "updated durable Codex review comment"
  },
  {
    "number": 44578,
    "action": "review_comment_synced",
    "reason": "updated durable Codex review comment"
  },
  {
    "number": 44588,
    "action": "review_comment_synced",
    "reason": "updated durable Codex review comment"
  },
  {
    "number": 44655,
    "action": "review_comment_synced",
    "reason": "updated durable Codex review comment"
  },
  {
    "number": 44683,
    "action": "review_comment_synced",
    "reason": "updated durable Codex review comment"
  },
  {
    "number": 44710,
    "action": "review_comment_synced",
    "reason": "updated durable Codex review comment"
  },
  {
    "number": 44811,
    "action": "review_comment_synced",
    "reason": "updated durable Codex review comment"
  },
  {
    "number": 44897,
    "action": "review_comment_synced",
    "reason": "updated durable Codex review comment"
  },
  {
    "number": 44925,
    "action": "review_comment_synced",
    "reason": "updated durable Codex review comment"
  },
  {
    "number": 45003,
    "action": "review_comment_synced",
    "reason": "updated durable Codex review comment"
  }
]