{
  "status": "executed",
  "generated_at": "2026-06-02T18:19:19.065Z",
  "repo": "openclaw/openclaw",
  "repair_repo": "openclaw/clawsweeper",
  "review_repo": "openclaw/clawsweeper",
  "since": "2026-06-02T15:19:18.376Z",
  "execute": true,
  "force_reprocess": false,
  "max_comments": 1,
  "item_numbers": [
    89548
  ],
  "comment_ids": [
    4604857203
  ],
  "status_comment_id": null,
  "max_autoclose_targets": 8,
  "scanned_comments": 1,
  "commands_seen": 1,
  "actionable": 0,
  "trusted_bots": [
    "clawsweeper[bot]",
    "openclaw-clawsweeper[bot]"
  ],
  "allowed_repository_permissions": [
    "admin",
    "maintain",
    "write"
  ],
  "max_auto_repairs_per_head": 2,
  "max_auto_repairs_per_pr": 10,
  "lookup_concurrency": 8,
  "commands": [
    {
      "idempotency_key": "clawsweeper-repair:openclaw/openclaw:89548:4604857203:2026-06-02T18:18:05Z:clawsweeper_auto_repair",
      "comment_id": "4604857203",
      "comment_version_key": "4604857203:2026-06-02T18:18:05Z",
      "comment_url": "https://github.com/openclaw/openclaw/pull/89548#issuecomment-4604857203",
      "repo": "openclaw/openclaw",
      "issue_number": 89548,
      "author": "clawsweeper[bot]",
      "author_id": 274271284,
      "author_association": "CONTRIBUTOR",
      "comment_created_at": "2026-06-02T17:04:31Z",
      "comment_updated_at": "2026-06-02T18:18:05Z",
      "status_comment_id": null,
      "trigger": "trusted_bot",
      "command": "clawsweeper auto repair",
      "intent": "clawsweeper_auto_repair",
      "autoclose_message": null,
      "implementation_prompt": null,
      "operator_override": null,
      "trusted_bot": true,
      "trusted_bot_author": "clawsweeper[bot]",
      "automation_source": "clawsweeper",
      "repair_reason": "structured ClawSweeper marker: fix-required (finding=review-feedback sha=67e1780e94ba8094bdb847dfd9977c00a3f4aed8)",
      "review_summary": "The branch makes `exec`/`bash` mutation classification command-sensitive with a narrow read-only allowlist and adds focused mutation helper tests.\n\nPR surface: Source +193, Tests +46. Total +239 across 2 files.\n\nReproducibility: yes. source-level: current main marks all `exec`/`bash` calls mutating and the payload builder uses that flag to decide final warning delivery. The PR body also provides terminal proof through the production mutation and payload builder path.",
      "review_followup": "- [P2] A narrow classifier/test repair can address the side-effect flag false negatives; the remaining blocker is not a product decision.",
      "freeform_prompt": null,
      "visual_lens": null,
      "expected_head_sha": "67e1780e94ba8094bdb847dfd9977c00a3f4aed8",
      "finding_id": "review-feedback",
      "status": "skipped",
      "actions": [],
      "reason": "comment version already processed in ledger"
    }
  ],
  "ledger_changed": true,
  "timings": {
    "total_ms": 1625,
    "phases": [
      {
        "name": "list_candidate_comments",
        "ms": 673
      },
      {
        "name": "prehydrate_command_lookups",
        "ms": 1
      },
      {
        "name": "classify_commands",
        "ms": 0
      },
      {
        "name": "execute_commands",
        "ms": 937
      },
      {
        "name": "append_ledger",
        "ms": 1
      }
    ]
  }
}
