{
  "status": "executed",
  "generated_at": "2026-05-24T21:31:08.513Z",
  "repo": "openclaw/openclaw",
  "repair_repo": "openclaw/clawsweeper",
  "review_repo": "openclaw/clawsweeper",
  "since": "2026-05-24T18:31:07.225Z",
  "execute": true,
  "force_reprocess": false,
  "max_comments": 1000,
  "item_numbers": [
    86207
  ],
  "comment_ids": [],
  "status_comment_id": null,
  "max_autoclose_targets": 8,
  "scanned_comments": 2,
  "commands_seen": 1,
  "actionable": 0,
  "trusted_bots": [
    "clawsweeper[bot]",
    "openclaw-clawsweeper[bot]"
  ],
  "allowed_repository_permissions": [
    "admin",
    "maintain",
    "write"
  ],
  "max_auto_repairs_per_head": 2,
  "max_auto_repairs_per_pr": 10,
  "lookup_concurrency": 8,
  "commands": [
    {
      "idempotency_key": "clawsweeper-repair:openclaw/openclaw:86207:4529997891:2026-05-24T21:31:03Z:clawsweeper_auto_repair",
      "comment_id": "4529997891",
      "comment_version_key": "4529997891:2026-05-24T21:31:03Z",
      "comment_url": "https://github.com/openclaw/openclaw/pull/86207#issuecomment-4529997891",
      "repo": "openclaw/openclaw",
      "issue_number": 86207,
      "author": "clawsweeper[bot]",
      "author_id": 274271284,
      "author_association": "CONTRIBUTOR",
      "comment_created_at": "2026-05-24T21:23:30Z",
      "comment_updated_at": "2026-05-24T21:31:03Z",
      "status_comment_id": null,
      "trigger": "trusted_bot",
      "command": "clawsweeper auto repair",
      "intent": "clawsweeper_auto_repair",
      "autoclose_message": null,
      "implementation_prompt": null,
      "trusted_bot": true,
      "trusted_bot_author": "clawsweeper[bot]",
      "automation_source": "clawsweeper",
      "repair_reason": "structured ClawSweeper needs-human verdict with repairable P-severity findings (sha=6552774f7ae8f4f50d1f6a47200b52059d380741)",
      "review_summary": "The PR broadens `openclaw.mjs` optional import miss detection to accept Bun-style `Cannot find module` messages and adds a VM-based regression test for launcher module-not-found matching.\n\nPR surface: Tests +46, Other +13. Total +59 across 2 files.\n\nReproducibility: yes. at source-helper level: current `main` returns `false` for the reported Bun-style message-only `./dist/warning-filter.js` miss, and the linked issue provides the full Bun/OpenClaw environment. I did not establish a full Bun startup run in this checkout.",
      "review_followup": "Needs contributor or maintainer revision for direct-only Bun matching plus real behavior proof; ClawSweeper should not take a repair lane while contributor proof is missing.",
      "freeform_prompt": null,
      "expected_head_sha": "6552774f7ae8f4f50d1f6a47200b52059d380741",
      "finding_id": null,
      "status": "skipped",
      "actions": [],
      "target": {
        "kind": "pull_request",
        "title": "fix: tolerate Bun launcher import misses",
        "body": "## Summary\n- match Bun direct module-miss messages for optional launcher imports that omit ERR_MODULE_NOT_FOUND\n- keep direct-miss matching scoped to the requested specifier or resolved path\n- add regression coverage for Bun-style launcher module-not-found messages\n\nFixes #86198\n\n## Tests\n- node scripts/run-vitest.mjs test/scripts/openclaw-launcher-module-not-found.test.ts\n- temp packaged-launcher smoke: bun ./openclaw.mjs loads dummy dist/entry.js without warning-filter.js present",
        "branch": "fix/86198-bun-warning-filter-miss",
        "head_sha": "6552774f7ae8f4f50d1f6a47200b52059d380741",
        "author": "zerone0x",
        "labels": [
          "size: S",
          "triage: needs-real-behavior-proof",
          "P1",
          "rating: 🦪 silver shellfish",
          "status: 📣 needs proof"
        ],
        "files": [
          {
            "path": "openclaw.mjs",
            "additions": 20,
            "deletions": 7,
            "changeType": "MODIFIED"
          },
          {
            "path": "test/scripts/openclaw-launcher-module-not-found.test.ts",
            "additions": 46,
            "deletions": 0,
            "changeType": "ADDED"
          }
        ],
        "is_clawsweeper_pr": false,
        "cluster_id": null,
        "job_path": null,
        "automerge_cluster_id": "automerge-openclaw-openclaw-86207",
        "automerge_job_path": "jobs/openclaw/inbox/automerge-openclaw-openclaw-86207.md",
        "mode": "autonomous",
        "mergeable": "MERGEABLE",
        "merge_state_status": "UNSTABLE",
        "review_decision": "",
        "checks": {
          "total": 20,
          "counts": {
            "CANCELLED": 2,
            "IN_PROGRESS": 1,
            "SKIPPED": 10,
            "SUCCESS": 7
          },
          "blockers": [
            "Real behavior proof:CANCELLED",
            "preflight:IN_PROGRESS"
          ],
          "pending": [
            "preflight:IN_PROGRESS"
          ],
          "terminalBlockers": [
            "Real behavior proof:CANCELLED"
          ]
        }
      },
      "reason": "repair commands require a ClawSweeper PR or a PR opted into ClawSweeper autofix or automerge"
    }
  ],
  "ledger_changed": true,
  "timings": {
    "total_ms": 1474,
    "phases": [
      {
        "name": "list_candidate_comments",
        "ms": 246
      },
      {
        "name": "prehydrate_command_lookups",
        "ms": 1033
      },
      {
        "name": "classify_commands",
        "ms": 2
      },
      {
        "name": "execute_commands",
        "ms": 181
      },
      {
        "name": "append_ledger",
        "ms": 1
      }
    ]
  }
}
