{
  "status": "executed",
  "generated_at": "2026-06-27T17:48:55.144Z",
  "repo": "openclaw/openclaw",
  "repair_repo": "openclaw/clawsweeper",
  "review_repo": "openclaw/clawsweeper",
  "since": "2026-06-27T14:48:52.941Z",
  "execute": true,
  "force_reprocess": false,
  "max_comments": 1000,
  "item_numbers": [
    97269
  ],
  "comment_ids": [],
  "status_comment_id": null,
  "max_autoclose_targets": 8,
  "scanned_comments": 3,
  "commands_seen": 2,
  "actionable": 0,
  "trusted_bots": [
    "clawsweeper[bot]",
    "openclaw-clawsweeper[bot]"
  ],
  "allowed_repository_permissions": [
    "admin",
    "maintain",
    "write"
  ],
  "max_auto_repairs_per_head": 2,
  "max_auto_repairs_per_pr": 10,
  "lookup_concurrency": 8,
  "commands": [
    {
      "idempotency_key": "clawsweeper-repair:openclaw/openclaw:97269:4818965425:2026-06-27T17:48:48Z:clawsweeper_needs_human",
      "comment_id": "4818965425",
      "comment_version_key": "4818965425:2026-06-27T17:48:48Z",
      "comment_url": "https://github.com/openclaw/openclaw/pull/97269#issuecomment-4818965425",
      "repo": "openclaw/openclaw",
      "target_branch": null,
      "issue_number": 97269,
      "author": "clawsweeper[bot]",
      "author_id": 274271284,
      "author_association": "CONTRIBUTOR",
      "comment_created_at": "2026-06-27T15:59:40Z",
      "comment_updated_at": "2026-06-27T17:48:48Z",
      "status_comment_id": null,
      "trigger": "trusted_bot",
      "command": "clawsweeper needs human",
      "intent": "clawsweeper_needs_human",
      "autoclose_message": null,
      "implementation_prompt": null,
      "operator_override": null,
      "trusted_bot": true,
      "trusted_bot_author": "clawsweeper[bot]",
      "automation_source": "clawsweeper",
      "repair_reason": "structured ClawSweeper verdict: needs-human (sha=da2fe8a2b3225ed52ed4fb26b9c831c63dd6eb77)",
      "review_summary": null,
      "review_followup": null,
      "freeform_prompt": null,
      "visual_lens": null,
      "expected_head_sha": "da2fe8a2b3225ed52ed4fb26b9c831c63dd6eb77",
      "close_reason": null,
      "close_confidence": null,
      "close_action_taken": null,
      "reviewed_at": null,
      "expected_item_updated_at": null,
      "expected_source_revision": null,
      "finding_id": null,
      "status": "skipped",
      "actions": [],
      "target": {
        "kind": "pull_request",
        "title": "improve: show edit mismatch candidate lines",
        "body": "﻿Closes #97032\n\n## What Problem This Solves\n\nResolves a problem where edit tool `oldText` mismatch failures only showed the generic exact-match error plus current file contents, leaving users to guess whether indentation, escaping, or nearby text drift caused the miss.\n\n## Why This Change Was Made\n\nThe edit mismatch path now appends bounded nearest-candidate diagnostics with line numbers, escaped line diffs, and indentation hints when the failing edit can be identified. Matching behavior is unchanged: the tool still requires the same exact/fuzzy edit semantics, and validation-phase no-op mismatch errors avoid candidate guesses when the indexed edit source is ambiguous.\n\n## User Impact\n\nUsers and agents get actionable feedback after a failed edit call: the error can point at nearby candidate lines and show the visible difference, while still preserving the existing current-file-content hint.\n\n## Evidence\n\n- Real behavior proof: ran `node --import tsx` against `createEditTool()` on a temp file and intentionally submitted an `oldText` indentation mismatch. Result: the thrown edit-tool error included `Nearest candidate lines:`, `Candidate 1 (line 2):`, `indentation: expected 6 spaces, candidate 2 spaces`, and escaped diff lines (`- \"      return value;\"` / `+ \"  return value;\"`) after the redacted `Current file contents:` block.\n- `node scripts/run-vitest.mjs src/agents/sessions/tools/edit.test.ts` - passed, 24 tests\n- `node scripts/run-vitest.mjs src/agents/agent-tools.create-openclaw-coding-tools.test.ts` - passed, 65 tests after rerun with a fresh `OPENCLAW_VITEST_FS_MODULE_CACHE_PATH`; an earlier same-command run hit a local transient `typebox` module-cache resolution error\n- `$env:OPENCLAW_OXLINT_SKIP_PREPARE='1'; node scripts/run-oxlint.mjs --tsconfig config/tsconfig/oxlint.core.json src/agents/sessions/tools/edit.ts src/agents/sessions/tools/edit.test.ts` - passed\n- `git diff --check` - passed\n- `python .agents\\skills\\autoreview\\scripts\\autoreview --mode local` - clean, no accepted/actionable findings reported; helper exited 0, with a Windows GBK stderr reader exception after the clean result\r\n",
        "branch": "codex/edit-mismatch-candidates",
        "head_sha": "da2fe8a2b3225ed52ed4fb26b9c831c63dd6eb77",
        "author": "qingminglong",
        "labels": [
          "agents",
          "size: M",
          "proof: sufficient",
          "P3",
          "rating: 🦐 gold shrimp",
          "merge-risk: 🚨 availability",
          "status: ⏳ waiting on author",
          "merge-risk: 🚨 other"
        ],
        "files": [
          {
            "path": "src/agents/sessions/tools/edit.test.ts",
            "additions": 110,
            "deletions": 1,
            "changeType": "MODIFIED"
          },
          {
            "path": "src/agents/sessions/tools/edit.ts",
            "additions": 223,
            "deletions": 4,
            "changeType": "MODIFIED"
          }
        ],
        "changedFiles": 2,
        "additions": 333,
        "deletions": 5,
        "is_clawsweeper_pr": false,
        "cluster_id": null,
        "job_path": null,
        "source_job_path": null,
        "has_automerge_job": false,
        "automerge_cluster_id": "automerge-openclaw-openclaw-97269",
        "automerge_job_path": "jobs/openclaw/inbox/automerge-openclaw-openclaw-97269.md",
        "mode": "autonomous",
        "mergeable": "MERGEABLE",
        "merge_state_status": "UNSTABLE",
        "review_decision": "",
        "checks": {
          "total": 97,
          "gatingTotal": 92,
          "counts": {
            "CANCELLED": 2,
            "SKIPPED": 31,
            "SUCCESS": 63,
            "NEUTRAL": 1
          },
          "blockers": [
            "Real behavior proof:CANCELLED"
          ],
          "pending": [
            "Real behavior proof:CANCELLED"
          ],
          "terminalBlockers": [],
          "externalBlockers": []
        }
      },
      "maintainer_authorized": false,
      "author_readonly_authorized": false,
      "reason": "PR is not opted into ClawSweeper autofix or automerge"
    },
    {
      "idempotency_key": "comment-router:openclaw/openclaw:97269:4819677516:2026-06-27T17:21:39Z:re_review",
      "comment_id": "4819677516",
      "comment_version_key": "4819677516:2026-06-27T17:21:39Z",
      "comment_url": "https://github.com/openclaw/openclaw/pull/97269#issuecomment-4819677516",
      "repo": "openclaw/openclaw",
      "target_branch": null,
      "issue_number": 97269,
      "author": "qingminglong",
      "author_id": 34085845,
      "author_association": "NONE",
      "comment_created_at": "2026-06-27T17:21:39Z",
      "comment_updated_at": "2026-06-27T17:21:39Z",
      "status_comment_id": null,
      "trigger": "mention",
      "command": "re-review",
      "intent": "re_review",
      "autoclose_message": null,
      "implementation_prompt": null,
      "operator_override": null,
      "trusted_bot": false,
      "trusted_bot_author": null,
      "automation_source": null,
      "repair_reason": null,
      "review_summary": null,
      "review_followup": null,
      "freeform_prompt": null,
      "visual_lens": null,
      "expected_head_sha": null,
      "close_reason": null,
      "close_confidence": null,
      "close_action_taken": null,
      "reviewed_at": null,
      "expected_item_updated_at": null,
      "expected_source_revision": null,
      "finding_id": null,
      "status": "skipped",
      "actions": [],
      "reason": "comment version already processed in ledger"
    }
  ],
  "ledger_changed": true,
  "timings": {
    "total_ms": 3309,
    "phases": [
      {
        "name": "list_candidate_comments",
        "ms": 397
      },
      {
        "name": "prehydrate_comment_commands",
        "ms": 1791
      },
      {
        "name": "classify_comment_commands",
        "ms": 2
      },
      {
        "name": "prehydrate_repair_loop_sweeps",
        "ms": 0
      },
      {
        "name": "classify_repair_loop_sweeps",
        "ms": 0
      },
      {
        "name": "execute_commands",
        "ms": 1095
      },
      {
        "name": "append_ledger",
        "ms": 1
      }
    ]
  }
}
