{
  "status": "executed",
  "generated_at": "2026-05-02T18:18:59.592Z",
  "repo": "openclaw/openclaw",
  "repair_repo": "openclaw/clawsweeper",
  "review_repo": "openclaw/clawsweeper",
  "since": "2026-05-02T15:18:57.439Z",
  "execute": true,
  "force_reprocess": false,
  "max_comments": 1000,
  "item_numbers": [
    63919
  ],
  "comment_ids": [],
  "max_autoclose_targets": 8,
  "scanned_comments": 7,
  "commands_seen": 1,
  "actionable": 0,
  "trusted_bots": [
    "clawsweeper[bot]",
    "openclaw-clawsweeper[bot]"
  ],
  "allowed_repository_permissions": [
    "admin",
    "maintain",
    "write"
  ],
  "max_auto_repairs_per_head": 1,
  "max_auto_repairs_per_pr": 10,
  "lookup_concurrency": 8,
  "commands": [
    {
      "idempotency_key": "clawsweeper-repair:openclaw/openclaw:63919:4323764251:2026-05-02T18:18:53Z:clawsweeper_needs_human",
      "comment_id": "4323764251",
      "comment_version_key": "4323764251:2026-05-02T18:18:53Z",
      "comment_url": "https://github.com/openclaw/openclaw/pull/63919#issuecomment-4323764251",
      "repo": "openclaw/openclaw",
      "issue_number": 63919,
      "author": "clawsweeper[bot]",
      "author_association": "CONTRIBUTOR",
      "comment_created_at": "2026-04-27T02:21:30Z",
      "comment_updated_at": "2026-05-02T18:18:53Z",
      "trigger": "trusted_bot",
      "command": "clawsweeper needs human",
      "intent": "clawsweeper_needs_human",
      "autoclose_message": null,
      "implementation_prompt": null,
      "trusted_bot": true,
      "trusted_bot_author": "clawsweeper[bot]",
      "automation_source": "clawsweeper",
      "repair_reason": "structured ClawSweeper verdict: needs-human (sha=ccbe3cb130f5e9946596462758159d95478bcc70)",
      "review_summary": "The PR adds an unwrapped raw coding-tool factory, wires coding primitives into Gateway HTTP `/tools/invoke` behind existing policy and deny-list gates, and updates tests, docs, and changelog.\n\nReproducibility: yes. Current main source reproduction is a `POST /tools/invoke` request for an allowlisted coding primitive such as `read`: the current resolver only materializes Gateway/OpenClaw tools, while the PR test coverage exercises the new successful and default-denied coding-tool paths.",
      "review_followup": "This is a security-sensitive Gateway execution-surface PR that appears ready for maintainer review; no narrow automated repair is identified.",
      "freeform_prompt": null,
      "expected_head_sha": "ccbe3cb130f5e9946596462758159d95478bcc70",
      "finding_id": null,
      "status": "skipped",
      "actions": [],
      "target": {
        "kind": "pull_request",
        "title": "feat(gateway): wire coding tools into /tools/invoke HTTP surface",
        "branch": "feat/tools-invoke-coding-tools-upstream",
        "head_sha": "ccbe3cb130f5e9946596462758159d95478bcc70",
        "author": "simonusa",
        "labels": [
          "docs",
          "gateway",
          "agents",
          "size: M"
        ],
        "is_clawsweeper_pr": false,
        "cluster_id": null,
        "job_path": null,
        "automerge_cluster_id": "automerge-openclaw-openclaw-63919",
        "automerge_job_path": "jobs/openclaw/inbox/automerge-openclaw-openclaw-63919.md",
        "mode": "autonomous",
        "mergeable": "MERGEABLE",
        "merge_state_status": "CLEAN",
        "review_decision": "",
        "checks": {
          "total": 103,
          "counts": {
            "CANCELLED": 1,
            "SKIPPED": 22,
            "SUCCESS": 79,
            "NEUTRAL": 1
          },
          "blockers": [],
          "pending": [],
          "terminalBlockers": []
        }
      },
      "reason": "PR is not opted into ClawSweeper autofix or automerge"
    }
  ],
  "ledger_changed": true,
  "timings": {
    "total_ms": 2304,
    "phases": [
      {
        "name": "list_candidate_comments",
        "ms": 271
      },
      {
        "name": "prehydrate_command_lookups",
        "ms": 1869
      },
      {
        "name": "classify_commands",
        "ms": 2
      },
      {
        "name": "execute_commands",
        "ms": 144
      },
      {
        "name": "append_ledger",
        "ms": 1
      }
    ]
  }
}
