{
  "status": "executed",
  "generated_at": "2026-05-08T19:43:22.445Z",
  "repo": "openclaw/openclaw",
  "repair_repo": "openclaw/clawsweeper",
  "review_repo": "openclaw/clawsweeper",
  "since": "2026-05-08T16:43:20.316Z",
  "execute": true,
  "force_reprocess": false,
  "max_comments": 1000,
  "item_numbers": [
    79249
  ],
  "comment_ids": [],
  "max_autoclose_targets": 8,
  "scanned_comments": 3,
  "commands_seen": 1,
  "actionable": 0,
  "trusted_bots": [
    "clawsweeper[bot]",
    "openclaw-clawsweeper[bot]"
  ],
  "allowed_repository_permissions": [
    "admin",
    "maintain",
    "write"
  ],
  "max_auto_repairs_per_head": 2,
  "max_auto_repairs_per_pr": 10,
  "lookup_concurrency": 8,
  "commands": [
    {
      "idempotency_key": "clawsweeper-repair:openclaw/openclaw:79249:4403482603:2026-05-08T19:43:10Z:clawsweeper_auto_repair",
      "comment_id": "4403482603",
      "comment_version_key": "4403482603:2026-05-08T19:43:10Z",
      "comment_url": "https://github.com/openclaw/openclaw/pull/79249#issuecomment-4403482603",
      "repo": "openclaw/openclaw",
      "issue_number": 79249,
      "author": "clawsweeper[bot]",
      "author_association": "CONTRIBUTOR",
      "comment_created_at": "2026-05-08T05:02:11Z",
      "comment_updated_at": "2026-05-08T19:43:10Z",
      "trigger": "trusted_bot",
      "command": "clawsweeper auto repair",
      "intent": "clawsweeper_auto_repair",
      "autoclose_message": null,
      "implementation_prompt": null,
      "trusted_bot": true,
      "trusted_bot_author": "clawsweeper[bot]",
      "automation_source": "clawsweeper",
      "repair_reason": "structured ClawSweeper needs-human verdict with repairable P-severity findings (sha=037d870ff902c65bb6d3ebcef1dae7e116352490)",
      "review_summary": "This PR changes plugin registry duplicate channel and channel-setup diagnostics, plus the changelog, to show the owning plugin and the plugin attempting re-registration.\n\nReproducibility: yes. for source reproduction: the current registry conflict path emits only the existing owner id, and the prefer-over test creates two plugins sharing the same channel id. I did not run a live conflicting-plugin setup in this read-only review.",
      "review_followup": "Contributor-supplied real behavior proof is still the merge gate, so this should stay in human PR review rather than a ClawSweeper repair lane.",
      "freeform_prompt": null,
      "expected_head_sha": "037d870ff902c65bb6d3ebcef1dae7e116352490",
      "finding_id": null,
      "status": "skipped",
      "actions": [],
      "target": {
        "kind": "pull_request",
        "title": "fix(plugins/registry): show both owner and requester in channel conflict diagnostics (#79239)",
        "branch": "fix/channel-conflict-diagnostic-plugin-id-79239",
        "head_sha": "037d870ff902c65bb6d3ebcef1dae7e116352490",
        "author": "hclsys",
        "labels": [
          "size: XS",
          "proof: supplied"
        ],
        "is_clawsweeper_pr": false,
        "cluster_id": null,
        "job_path": null,
        "automerge_cluster_id": "automerge-openclaw-openclaw-79249",
        "automerge_job_path": "jobs/openclaw/inbox/automerge-openclaw-openclaw-79249.md",
        "mode": "autonomous",
        "mergeable": "MERGEABLE",
        "merge_state_status": "UNSTABLE",
        "review_decision": "",
        "checks": {
          "total": 87,
          "counts": {
            "QUEUED": 36,
            "SUCCESS": 41,
            "SKIPPED": 10
          },
          "blockers": [
            "Security High (core-auth-secrets):QUEUED",
            "Select Critical Quality shards:QUEUED",
            "Scan changed paths (precise):QUEUED",
            "Security High (channel-runtime-boundary):QUEUED",
            "Security High (network-ssrf-boundary):QUEUED",
            "Security High (mcp-process-tool-boundary):QUEUED",
            "Security High (plugin-trust-boundary):QUEUED",
            "Security High (actions):QUEUED",
            "build-artifacts:QUEUED",
            "checks-fast-bundled:QUEUED",
            "checks-fast-contracts-plugins-a:QUEUED",
            "checks-fast-contracts-plugins-b:QUEUED",
            "checks-fast-contracts-plugins-c:QUEUED",
            "checks-fast-contracts-plugins-d:QUEUED",
            "checks-fast-contracts-channels-a:QUEUED",
            "checks-fast-contracts-channels-b:QUEUED",
            "checks-fast-contracts-channels-c:QUEUED",
            "checks-node-core-runtime-infra-state:QUEUED",
            "checks-node-core-runtime-infra-process:QUEUED",
            "checks-node-agentic-control-plane-agent-chat:QUEUED",
            "checks-node-agentic-control-plane-auth-node:QUEUED",
            "checks-node-agentic-control-plane-http-models:QUEUED",
            "checks-node-agentic-control-plane-http-plugin-ws:QUEUED",
            "checks-node-agentic-control-plane-runtime:QUEUED",
            "checks-node-agentic-control-plane-startup-runtime:QUEUED",
            "check-prod-types:QUEUED",
            "check-lint:QUEUED",
            "check-test-types:QUEUED",
            "check-additional-boundaries-a:QUEUED",
            "check-additional-boundaries-b:QUEUED",
            "check-additional-boundaries-c:QUEUED",
            "check-additional-boundaries-d:QUEUED",
            "check-additional-extension-channels:QUEUED",
            "check-additional-extension-bundled:QUEUED",
            "check-additional-extension-package-boundary:QUEUED",
            "check-additional-runtime-topology-architecture:QUEUED"
          ],
          "pending": [
            "Security High (core-auth-secrets):QUEUED",
            "Select Critical Quality shards:QUEUED",
            "Scan changed paths (precise):QUEUED",
            "Security High (channel-runtime-boundary):QUEUED",
            "Security High (network-ssrf-boundary):QUEUED",
            "Security High (mcp-process-tool-boundary):QUEUED",
            "Security High (plugin-trust-boundary):QUEUED",
            "Security High (actions):QUEUED",
            "build-artifacts:QUEUED",
            "checks-fast-bundled:QUEUED",
            "checks-fast-contracts-plugins-a:QUEUED",
            "checks-fast-contracts-plugins-b:QUEUED",
            "checks-fast-contracts-plugins-c:QUEUED",
            "checks-fast-contracts-plugins-d:QUEUED",
            "checks-fast-contracts-channels-a:QUEUED",
            "checks-fast-contracts-channels-b:QUEUED",
            "checks-fast-contracts-channels-c:QUEUED",
            "checks-node-core-runtime-infra-state:QUEUED",
            "checks-node-core-runtime-infra-process:QUEUED",
            "checks-node-agentic-control-plane-agent-chat:QUEUED",
            "checks-node-agentic-control-plane-auth-node:QUEUED",
            "checks-node-agentic-control-plane-http-models:QUEUED",
            "checks-node-agentic-control-plane-http-plugin-ws:QUEUED",
            "checks-node-agentic-control-plane-runtime:QUEUED",
            "checks-node-agentic-control-plane-startup-runtime:QUEUED",
            "check-prod-types:QUEUED",
            "check-lint:QUEUED",
            "check-test-types:QUEUED",
            "check-additional-boundaries-a:QUEUED",
            "check-additional-boundaries-b:QUEUED",
            "check-additional-boundaries-c:QUEUED",
            "check-additional-boundaries-d:QUEUED",
            "check-additional-extension-channels:QUEUED",
            "check-additional-extension-bundled:QUEUED",
            "check-additional-extension-package-boundary:QUEUED",
            "check-additional-runtime-topology-architecture:QUEUED"
          ],
          "terminalBlockers": []
        }
      },
      "reason": "repair commands require a ClawSweeper PR or a PR opted into ClawSweeper autofix or automerge"
    }
  ],
  "ledger_changed": true,
  "timings": {
    "total_ms": 2515,
    "phases": [
      {
        "name": "list_candidate_comments",
        "ms": 471
      },
      {
        "name": "prehydrate_command_lookups",
        "ms": 1645
      },
      {
        "name": "classify_commands",
        "ms": 2
      },
      {
        "name": "execute_commands",
        "ms": 375
      },
      {
        "name": "append_ledger",
        "ms": 1
      }
    ]
  }
}
